physical_spline/__init__.py
physical_spline/spline_designer.py
physical_spline/utils/lgs_fitting_elements.py
physical_spline/utils/lgs_regularisation_elements.py
physical_spline/utils/matrix_operations.py
physical_spline/utils/simple_fitting.py
physical_spline/utils/spline_evaluator.py
physical_spline-0.1.1.dist-info/METADATA
physical_spline-0.1.1.dist-info/WHEEL
physical_spline-0.1.1.dist-info/top_level.txt
physical_spline-0.1.1.dist-info/RECORD
