Metadata-Version: 2.4
Name: physical_spline
Version: 0.1.1
Summary: Physical spline designer and evaluator
Author: Jonas Torzewski
Requires-Python: >=3.8
Requires-Dist: numpy
Requires-Dist: scipy
Requires-Dist: pandas
